{
    "slug": "hierarchy-of-laws",
    "type": "lesson",
    "title": "Иерархия законов",
    "isViewed": false,
    "video": {
        "src": "0419.mp4",
        "poster": "/assets/media/posters/m7/lesson4.jpg",
        "mimeType": "video/mp4"
    },
    "description": "## Конспект урока «2.4. Иерархия законов»\n\n### 1. Введение\nЗаконы - не хаотичный набор правил, а стройная пирамида, где у каждого документа свое место и своя сила.\n\n### 2. Зачем нужна иерархия законов\nБез четкой системы возникла бы путаница: один закон противоречил бы другому.\n\nИерархия:\n- определяет, какой закон главнее;\n- помогает разрешать конфликты между нормами;\n- обеспечивает единство правовой системы.\n\n### 3. Структура иерархии\n#### 1. Конституция РФ\n- вершина пирамиды, основной закон страны;\n- ни один документ не может ей противоречить;\n- гарантирует базовые права: на жизнь, свободу слова, образование и т.д.\n\n#### 2. Международные договоры\n- становятся частью правовой системы после подписания и ратификации;\n- не могут противоречить Конституции.\n\n#### 3. Федеральные конституционные законы\n- принимаются по особым вопросам, указанным в Конституции;\n- важнее обычных федеральных законов, но ниже Конституции.\n\n#### 4. Федеральные законы\n- регулируют почти все: от школ до дорог;\n- не могут противоречить Конституции и ФКЗ.\n\n#### 5. Подзаконные акты\n- указы Президента;\n- постановления Правительства;\n- приказы министерств;\n- если конфликтуют с законом, их отменяют.\n\n#### 6. Законы субъектов РФ\n- принимаются регионами;\n- не должны противоречить Конституции и федеральным законам.\n\n#### 7. Муниципальные акты\n- решения городских или сельских советов;\n- действуют только на территории конкретного муниципалитета.\n\n### 4. Принципы действия законов\n- Закон обратной силы не имеет.\n- Незнание закона не освобождает от ответственности.\n- Все законы должны быть опубликованы, иначе они не действуют.\n\n### 5. Практический пример: шум во дворе поздним вечером\nСитуация: группа ребят громко слушает музыку во дворе, соседи жалуются, вызывают полицию.\n\n#### По уровням иерархии\n1. Конституция РФ - права и свободы должны осуществляться с уважением прав других лиц.\n2. Международные договоры - защищают право на уважение частной и семейной жизни.\n3. ФКЗ - определяют систему судов, которые рассматривают споры.\n4. Федеральные законы - создают общую рамку и позволяют регионам вводить правила тишины.\n5. Законы субъекта РФ - устанавливают часы тишины и размеры штрафов.\n6. Подзаконные акты - разъясняют, как применять закон.\n7. Локальные акты - могут вводить дополнительные ограничения, если не противоречат закону.\n8. Полиция - проверяет время, уровень шума, наличие правил и применяет меры.\n\n#### Выводы из примера\n- права не безграничны;\n- законы работают как лестница;\n- если нижестоящий акт противоречит вышестоящему, действует вышестоящий.\n\n### 6. Почему это важно\nДаже в повседневной жизни ты сталкиваешься с законами:\n- при устройстве на первую работу;\n- в школе;\n- на улице;\n- в магазине.\n\nЗнание иерархии законов помогает:\n- защищать свои права;\n- понимать, почему принимаются те или иные решения;\n- быть ответственным гражданином.\n\n### 7. Итоговые выводы\nИерархия законов - это система защиты и порядка.\n\n- Конституция гарантирует базовые права.\n- Региональные законы уточняют правила для местности.\n- Локальные акты могут дополнять, но не заменять законы.\n- Все законы должны быть опубликованы.\n- Полиция и суды следят за исполнением.\n\nЗная эту систему, ты сможешь:\n- понимать, что разрешено, а что нет;\n- отстаивать свои права, опираясь на закон;\n- уважать права других.\n\n### Домашнее задание\n1. Выбери одну повседневную ситуацию и разбери ее по уровням иерархии законов.\n2. Приведи 2 примера законов или актов разных уровней, которые касаются твоей жизни.\n3. Напиши 3-4 предложения своими словами, почему важно, чтобы законы не противоречили друг другу.",
    "navigation": {
        "prev": "law-as-main-source",
        "next": "main-codes-of-rf"
    },
    "progress": {
        "completed": 0,
        "total": 5
    }
}